bigbang/__init__.py
bigbang/archive.py
bigbang/domain.py
bigbang/entity_resolution.py
bigbang/get_dependencies.py
bigbang/git_repo.py
bigbang/graph.py
bigbang/listserv.py
bigbang/mailman.py
bigbang/parse.py
bigbang/plot.py
bigbang/process.py
bigbang/repo_loader.py
bigbang/thread.py
bigbang/twopeople.py
bigbang/utils.py
bigbang/w3crawl.py
datactive_bigbang/__init__.py
datactive_bigbang/archive.py
datactive_bigbang/domain.py
datactive_bigbang/entity_resolution.py
datactive_bigbang/get_dependencies.py
datactive_bigbang/git_repo.py
datactive_bigbang/graph.py
datactive_bigbang/listserv.py
datactive_bigbang/mailman.py
datactive_bigbang/parse.py
datactive_bigbang/plot.py
datactive_bigbang/process.py
datactive_bigbang/repo_loader.py
datactive_bigbang/thread.py
datactive_bigbang/twopeople.py
datactive_bigbang/utils.py
datactive_bigbang/w3crawl.py
dbigbang/__init__.py
dbigbang/archive.py
dbigbang/domain.py
dbigbang/entity_resolution.py
dbigbang/get_dependencies.py
dbigbang/git_repo.py
dbigbang/graph.py
dbigbang/listserv.py
dbigbang/mailman.py
dbigbang/parse.py
dbigbang/plot.py
dbigbang/process.py
dbigbang/repo_loader.py
dbigbang/thread.py
dbigbang/twopeople.py
dbigbang/utils.py
dbigbang/w3crawl.py
DBigBang-0.2.dist-info/LICENSE
DBigBang-0.2.dist-info/METADATA
DBigBang-0.2.dist-info/WHEEL
DBigBang-0.2.dist-info/top_level.txt
DBigBang-0.2.dist-info/RECORD
