Metadata-Version: 2.1
Name: DBigBang
Version: 0.2
Summary: Analysis of Mailman archives
Home-page: https://gitbub.com/datactive/dbigbang
Author: Sebastian Benthall
Author-email: sb@ischool.berkeley.edu
License: UNKNOWN
Download-URL: https://gitbub.com/datactive/dbigbang
Platform: UNKNOWN
Requires-Dist: beautifulsoup4
Requires-Dist: chardet
Requires-Dist: common
Requires-Dist: coverage
Requires-Dist: html2text
Requires-Dist: ipython
Requires-Dist: jinja2
Requires-Dist: jsonschema
Requires-Dist: matplotlib
Requires-Dist: networkx
Requires-Dist: numpy
Requires-Dist: pandas
Requires-Dist: powerlaw
Requires-Dist: pytest
Requires-Dist: python-Levenshtein
Requires-Dist: python-dateutil
Requires-Dist: pytz
Requires-Dist: pyyaml
Requires-Dist: pyzmq
Requires-Dist: requests
Requires-Dist: tornado
